persist_ext/__init__.py
persist_ext/_version.py
persist_ext/internals/__init__.py
persist_ext/internals/persist_magics.py
persist_ext/internals/data/generated.py
persist_ext/internals/data/get_generated_df.py
persist_ext/internals/data/idfy.py
persist_ext/internals/data/prepare.py
persist_ext/internals/data/process_generate_dataset.py
persist_ext/internals/data/utils.py
persist_ext/internals/data/validate.py
persist_ext/internals/intent_inference/tests/test_intent.py
persist_ext/internals/plot/__init__.py
persist_ext/internals/plot/barchart.py
persist_ext/internals/plot/plot_helpers.py
persist_ext/internals/plot/scatterplot.py
persist_ext/internals/utils/dev.py
persist_ext/internals/utils/dt_helpers.py
persist_ext/internals/utils/entry_paths.py
persist_ext/internals/utils/logger.py
persist_ext/internals/widgets/basepaths.json
persist_ext/internals/widgets/widget_map.json
persist_ext/internals/widgets/base/base_anywidget.py
persist_ext/internals/widgets/base/body_widget_base.py
persist_ext/internals/widgets/base/output_processor.py
persist_ext/internals/widgets/base/widget_with_chart.py
persist_ext/internals/widgets/base/widget_with_data.py
persist_ext/internals/widgets/base/widget_with_generation.py
persist_ext/internals/widgets/base/widget_with_intents.py
persist_ext/internals/widgets/base/widget_with_interactions.py
persist_ext/internals/widgets/base/widget_with_trrack.py
persist_ext/internals/widgets/interactions/annotation.py
persist_ext/internals/widgets/interactions/categorize.py
persist_ext/internals/widgets/interactions/selection.py
persist_ext/internals/widgets/persist_output/widget.py
persist_ext/internals/widgets/persist_output/wrappers.py
persist_ext/internals/widgets/vegalite_chart/parameters.py
persist_ext/internals/widgets/vegalite_chart/utils.py
persist_ext/labextension/static/lib_index_js.8b8fd816e26e671f9935.js
persist_ext/labextension/static/lib_index_js.8b8fd816e26e671f9935.js.map
persist_ext-1.6.2.dist-info/METADATA
persist_ext-1.6.2.dist-info/WHEEL
persist_ext-1.6.2.dist-info/licenses/LICENSE
persist_ext-1.6.2.dist-info/RECORD
