Metadata-Version: 2.3
Name: persist_ext
Version: 1.6.2
Dynamic: Keywords
Summary: PersIst is a JupyterLab extension to enable persistent interactive visualizations in JupyterLab notebooks.
Project-URL: Homepage, https://github.com/visdesignlab/persist
Project-URL: Bug Tracker, https://github.com/visdesignlab/persist/issues
Project-URL: Repository, https://github.com/visdesignlab/persist.git
Author-email: Kiran Gadhave <kirangadhave2@gmail.com>
License: BSD 3-Clause License
License-File: LICENSE
Classifier: Framework :: Jupyter
Classifier: Framework :: Jupyter :: JupyterLab
Classifier: Framework :: Jupyter :: JupyterLab :: 4
Classifier: Framework :: Jupyter :: JupyterLab :: Extensions
Classifier: Framework :: Jupyter :: JupyterLab :: Extensions :: Prebuilt
Classifier: License :: OSI Approved :: BSD License
Classifier: Programming Language :: Python
Classifier: Programming Language :: Python :: 3
Classifier: Programming Language :: Python :: 3.8
Classifier: Programming Language :: Python :: 3.9
Classifier: Programming Language :: Python :: 3.10
Classifier: Programming Language :: Python :: 3.11
Requires-Python: >=3.8
Requires-Dist: altair>=5
Requires-Dist: anywidget
Requires-Dist: fastparquet
Requires-Dist: ipywidgets
Requires-Dist: jupyterlab>=4
Requires-Dist: lzstring
Requires-Dist: pandas>=0.25
Requires-Dist: pyarrow
Requires-Dist: scikit-learn
Requires-Dist: traittypes==0.2.1
Provides-Extra: dev
Requires-Dist: ruff; extra == 'dev'
Requires-Dist: vega-datasets; extra == 'dev'
